{
	"versions": {
		"1.7.10": {
			"version": "2.5.1",
			"remote": "https://minecraft.curseforge.com/projects/sign-picture/files/2349401",
			"local": "SignPicture-1.7.10-2.5.1-universal.jar",
			"message": "Fix iChunUtil conflict bug",
			"message_local": {
				"ja_JP": "iChunUtil Modとの競合を解決しました"
			}
		},
		"1.8.9": {
			"version": "2.5.1",
			"remote": "https://minecraft.curseforge.com/projects/sign-picture/files/2349402/download",
			"local": "SignPicture-1.8.9-2.5.1-universal.jar",
			"message": "Fix iChunUtil conflict bug",
			"message_local": {
				"ja_JP": "iChunUtil Modとの競合を解決しました"
			}
		},
		"1.9.4": {
			"version": "2.5.1",
			"remote": "https://minecraft.curseforge.com/projects/sign-picture/files/2349403/download",
			"local": "SignPicture-1.9.4-2.5.1-universal.jar",
			"message": "Fix iChunUtil conflict bug",
			"message_local": {
				"ja_JP": "iChunUtil Modとの競合を解決しました"
			}
		},
		"1.10.2": {
			"version": "2.5.1",
			"remote": "https://minecraft.curseforge.com/projects/sign-picture/files/2349404/download",
			"local": "SignPicture-1.10.2-2.5.1-universal.jar",
			"message": "Fix iChunUtil conflict bug",
			"message_local": {
				"ja_JP": "iChunUtil Modとの競合を解決しました"
			}
		},
		"1.11": {
			"version": "2.5.1",
			"remote": "https://minecraft.curseforge.com/projects/sign-picture/files/2349405/download",
			"local": "SignPicture-1.11-2.5.1-universal.jar",
			"message": "Fix iChunUtil conflict bug",
			"message_local": {
				"ja_JP": "iChunUtil Modとの競合を解決しました"
			}
		}
	},
	"apis": {
		"image": {
			"gyazo": {
				"config": [
					{
						"clientid": "6dceb988be0fad140e544f9e2ec830bb83014b6cde9766049d03d88bdf3884f1"
					}
				]
			},
			"imgur": {
				"config": [
					{
						"clientid": "7896a166a54f0bc"
					}
				]
			}
		}
	},
	"website": "https://minecraft.curseforge.com/projects/sign-picture",
	"changelog": "https://github.com/Team-Fruit/SignPicture/releases",
	"private_msg": "http://fruit.bebehp.com/signpic.php/msg?id=%id%&name=%name%&vmod=%modversion%&vmodmc=%modmcversion%&vmodforge=%modforgeversion%&vmc=%mcversion%&vforge=%forgeversion%"
}